pebblo/__init__.py
pebblo/app/__init__.py
pebblo/app/daemon.py
pebblo/app/api/__init__.py
pebblo/app/api/api.py
pebblo/app/config/__init__.py
pebblo/app/config/config.py
pebblo/app/config/service.py
pebblo/app/enums/__init__.py
pebblo/app/enums/enums.py
pebblo/app/libs/__init__.py
pebblo/app/libs/logger.py
pebblo/app/models/__init__.py
pebblo/app/models/models.py
pebblo/app/routers/__init__.py
pebblo/app/routers/routers.py
pebblo/app/service/__init__.py
pebblo/app/service/discovery_service.py
pebblo/app/service/doc_helper.py
pebblo/app/service/service.py
pebblo/app/utils/__init__.py
pebblo/app/utils/utils.py
pebblo/entity_classifier/__init__.py
pebblo/entity_classifier/entity_classifier.py
pebblo/entity_classifier/libs/__init__.py
pebblo/entity_classifier/libs/logger.py
pebblo/entity_classifier/utils/__init__.py
pebblo/entity_classifier/utils/config.py
pebblo/entity_classifier/utils/regex_pattern.py
pebblo/entity_classifier/utils/utils.py
pebblo/reports/__init__.py
pebblo/reports/reports.py
pebblo/reports/assets/app-logo.svg
pebblo/reports/assets/aws-logo.svg
pebblo/reports/assets/cover-page-background.png
pebblo/reports/assets/csv-icon.svg
pebblo/reports/enums/__init__.py
pebblo/reports/enums/report_libraries.py
pebblo/reports/html_to_pdf_generator/__init__.py
pebblo/reports/html_to_pdf_generator/generator_functions.py
pebblo/reports/html_to_pdf_generator/report_generator.py
pebblo/reports/libs/logger.py
pebblo/reports/templates/index.css
pebblo/reports/templates/weasyprintTemplate.html
pebblo/reports/templates/xhtml2pdfTemplate.html
pebblo/topic_classifier/__init__.py
pebblo/topic_classifier/config.py
pebblo/topic_classifier/topic_classifier.py
pebblo/topic_classifier/enums/__init__.py
pebblo/topic_classifier/enums/constants.py
pebblo/topic_classifier/libs/__init__.py
pebblo/topic_classifier/libs/logger.py
pebblo_sample-0.1.11.dist-info/LICENSE
pebblo_sample-0.1.11.dist-info/METADATA
pebblo_sample-0.1.11.dist-info/WHEEL
pebblo_sample-0.1.11.dist-info/entry_points.txt
pebblo_sample-0.1.11.dist-info/top_level.txt
pebblo_sample-0.1.11.dist-info/RECORD
