Metadata-Version: 2.1
Name: pebblo-sample
Version: 0.1.11
Summary: Pebblo Gen-AI Data Analyzer
Author-email: Pebblo Authors <pebblo@daxa.ai>
Maintainer-email: Pebblo Maintainer <pebblo@daxa.ai>
Project-URL: Homepage, https://github.com/daxa-ai/pebblo
Project-URL: Bug Reports, https://github.com/daxa-ai/pebblo/issues
Project-URL: Funding, https://donate.pypi.org
Project-URL: Source, https://github.com/daxa-ai/pebblo/
Keywords: langchain,ai,rag
Classifier: Development Status :: 3 - Alpha
Classifier: Intended Audience :: Developers
Classifier: Topic :: Software Development :: Build Tools
Classifier: License :: Other/Proprietary License
Classifier: Operating System :: OS Independent
Classifier: Programming Language :: Python :: 3
Classifier: Programming Language :: Python :: 3.9
Classifier: Programming Language :: Python :: 3.10
Classifier: Programming Language :: Python :: 3.11
Classifier: Programming Language :: Python :: 3.12
Requires-Python: >=3.9
License-File: LICENSE
Requires-Dist: fastapi ==0.109.0
Requires-Dist: uvicorn ==0.25.0
Requires-Dist: pydantic ==1.10.8
Requires-Dist: presidio-analyzer ==2.2.351
Requires-Dist: presidio-anonymizer ==2.2.351
Requires-Dist: torch >=2.1.2
Requires-Dist: transformers ==4.36.2
Requires-Dist: jinja2 >=3.1.3
Requires-Dist: tqdm
Requires-Dist: xhtml2pdf ==0.2.15
Requires-Dist: weasyprint ==60.2
Provides-Extra: dev
Requires-Dist: check-manifest ; extra == 'dev'
Provides-Extra: test
Requires-Dist: ruff ; extra == 'test'
